agentrank/__init__.py
agentrank/embedder.py
agentrank-0.1.3.dist-info/METADATA
agentrank-0.1.3.dist-info/WHEEL
agentrank-0.1.3.dist-info/top_level.txt
agentrank-0.1.3.dist-info/RECORD
