Metadata-Version: 2.4
Name: agentrank
Version: 0.1.3
Summary: Temporal-aware embedding model for AI agent memory retrieval. The first embedder that understands WHEN memories happened.
Author-email: Vrushket More <vrushket2604@gmail.com>
License: Apache-2.0
Project-URL: Homepage, https://github.com/vmore2/AgentRank-base
Project-URL: Documentation, https://huggingface.co/vrushket/agentrank-base
Project-URL: Repository, https://github.com/vmore2/AgentRank-base
Project-URL: Issues, https://github.com/vmore2/AgentRank-base/issues
Keywords: embeddings,transformers,ai-agents,memory,retrieval,rag,vector-search,temporal,llm
Classifier: Development Status :: 4 - Beta
Classifier: Intended Audience :: Developers
Classifier: License :: OSI Approved :: Apache Software License
Classifier: Programming Language :: Python :: 3
Classifier: Programming Language :: Python :: 3.8
Classifier: Programming Language :: Python :: 3.9
Classifier: Programming Language :: Python :: 3.10
Classifier: Programming Language :: Python :: 3.11
Classifier: Topic :: Scientific/Engineering :: Artificial Intelligence
Requires-Python: >=3.8
Requires-Dist: torch>=1.9.0
Requires-Dist: transformers>=4.20.0
Requires-Dist: huggingface-hub>=0.14.0
Provides-Extra: dev
Requires-Dist: pytest>=7.0.0; extra == "dev"
Requires-Dist: black>=22.0.0; extra == "dev"
Requires-Dist: flake8>=4.0.0; extra == "dev"
